ANI_STT/__init__.py
aniket_stt-1.0.0.dist-info/METADATA
aniket_stt-1.0.0.dist-info/WHEEL
aniket_stt-1.0.0.dist-info/top_level.txt
aniket_stt-1.0.0.dist-info/RECORD
