Metadata-Version: 2.4
Name: ANIKET-STT
Version: 1.0.0
Summary: A simple Speech to Text converter using Selenium and Webdriver
Author: Aniket Rana
Author-email: aniketrana5892@gmail.com
Dynamic: author
Dynamic: author-email
Dynamic: summary
